api/__init__.py
lcra/__init__.py
lcra/cli.py
scraper/__init__.py
lcra-0.3.0.dist-info/METADATA
lcra-0.3.0.dist-info/WHEEL
lcra-0.3.0.dist-info/entry_points.txt
lcra-0.3.0.dist-info/RECORD
