Metadata-Version: 2.4
Name: lcra
Version: 0.3.0
Summary: A Python library and CLI tool for extracting flood status, lake levels, river conditions, and floodgate operations from the LCRA Hydromet system
Project-URL: Homepage, https://github.com/lancereinsmith/lcra
Project-URL: Documentation, https://lancereinsmith.github.io/lcra
Project-URL: Repository, https://github.com/lancereinsmith/lcra
Project-URL: Issues, https://github.com/lancereinsmith/lcra/issues
Project-URL: Changelog, https://lancereinsmith.github.io/lcra/changelog/
Author: LCRA Contributors
License: MIT
Keywords: colorado-river,flood,hydromet,lcra,texas,water-levels
Classifier: Development Status :: 4 - Beta
Classifier: Intended Audience :: Developers
Classifier: License :: OSI Approved :: MIT License
Classifier: Programming Language :: Python :: 3
Classifier: Programming Language :: Python :: 3.12
Classifier: Programming Language :: Python :: 3.13
Classifier: Programming Language :: Python :: 3.14
Classifier: Topic :: Scientific/Engineering
Classifier: Topic :: Utilities
Requires-Python: >=3.12
Requires-Dist: click>=8.3.1
Requires-Dist: fastapi>=0.128.0
Requires-Dist: httpx>=0.28.1
Requires-Dist: pydantic>=2.12.5
Requires-Dist: rich>=14.3.1
Requires-Dist: uvicorn[standard]>=0.40.0
